ambition_lists/__init__.py
ambition_lists/admin.py
ambition_lists/admin_site.py
ambition_lists/apps.py
ambition_lists/list_data.py
ambition_lists/models.py
ambition_lists/urls.py
ambition_lists/migrations/0001_initial.py
ambition_lists/migrations/0002_auto_20181206_2255.py
ambition_lists/migrations/0003_auto_20190305_0123.py
ambition_lists/migrations/0004_arvregimens.py
ambition_lists/migrations/0005_auto_20190523_1512.py
ambition_lists/migrations/0006_auto_20190529_0431.py
ambition_lists/migrations/0007_auto_20190628_2216.py
ambition_lists/migrations/0008_auto_20191108_0752.py
ambition_lists/migrations/0009_auto_20191120_0418.py
ambition_lists/migrations/__init__.py
ambition_lists/tests/__init__.py
ambition_lists/tests/test_preload.py
ambition_lists-0.1.16.dist-info/LICENSE
ambition_lists-0.1.16.dist-info/METADATA
ambition_lists-0.1.16.dist-info/WHEEL
ambition_lists-0.1.16.dist-info/top_level.txt
ambition_lists-0.1.16.dist-info/RECORD
