Metadata-Version: 2.1
Name: ambition-lists
Version: 0.1.16
Summary: List models for the ambition trial
Home-page: https://github.com/ambition-trial/ambition-lists
Author: Erik van Widenfelt
Author-email: ew2789@gmail.com
License: GPL license, see LICENSE
Keywords: django ambition edc lists
Platform: UNKNOWN
Classifier: Environment :: Web Environment
Classifier: Framework :: Django
Classifier: Intended Audience :: Developers
Classifier: Intended Audience :: Science/Research
Classifier: License :: OSI Approved :: GNU General Public License v3 (GPLv3)
Classifier: Operating System :: OS Independent
Classifier: Programming Language :: Python :: 3.7
Classifier: Topic :: Internet :: WWW/HTTP
Classifier: Topic :: Internet :: WWW/HTTP :: Dynamic Content
Requires-Python: >=3.7
Requires-Dist: ambition-form-validators
Requires-Dist: edc-constants
Requires-Dist: edc-list-data
Requires-Dist: edc-model
